Workbook
Name SegmentaciónDeDatos_Area: #N/A
Name SegmentaciónDeDatos_Estado: #N/A

Sheet BD
A1: Empleado_ID | B1: Nombre | C1: Área | D1: Cargo | E1: Ciudad | F1: Salario_Base
A2: E001 | B2: Laura Gómez | C2: Tecnología | D2: Desarrollador | E2: Bogotá | F2: 4200000
A3: E002 | B3: Juan Pérez | C3: Tecnología | D3: Analista | E3: Medellín | F3: 3900000
A4: E003 | B4: Camila Torres | C4: Ventas | D4: Ejecutivo | E4: Cali | F4: 3200000
A5: E004 | B5: Andrés Ruiz | C5: Ventas | D5: Supervisor | E5: Bogotá | F5: 4500000
A6: E005 | B6: Natalia Díaz | C6: Recursos Humanos | D6: Analista | E6: Medellín | F6: 3500000
A7: E006 | B7: Felipe Castro | C7: Finanzas | D7: Contador | E7: Bogotá | F7: 4300000
A8: E007 | B8: Daniela Rojas | C8: Marketing | D8: Diseñador | E8: Cali | F8: 3600000
A9: E008 | B9: Carlos Herrera | C9: Tecnología | D9: Soporte | E9: Barranquilla | F9: 3100000
A10: E009 | B10: María López | C10: Logística | D10: Coordinador | E10: Bogotá | F10: 4100000
A11: E010 | B11: Sebastián Gil | C11: Compras | D11: Analista | E11: Medellín | F11: 3400000
A12: E011 | B12: Paula Ramírez | C12: Marketing | D12: Community Manager | E12: Cali | F12: 3000000
A13: E012 | B13: David Sánchez | C13: Logística | D13: Auxiliar | E13: Barranquilla | F13: 2500000
... A16: E015 | B16: Valentina Cruz | C16: Recursos Humanos | D16: Coordinador | E16: Cali | F16: 4200000

Sheet DATOS
A1: Fecha | B1: Empleado_ID | C1: Días_Trabajados | D1: Horas_Extras | E1: Bonificación | F1: Descuento | G1: Nombre | H1: Cargo | I1: Area | J1: Ciudad | K1: Salario base | L1: Pago horas extra | M1: Salario total | N1: Estado
A2: 46204 | B2: E001 | C2: 22 | D2: 10 | E2: 250000 | F2: 50000 | G2: =_xlfn.XLOOKUP(B2,BD!A:A,BD!B:B) -> Laura Gómez | H2: =_xlfn.XLOOKUP(B2,BD!A:A,BD!D:D) -> Desarrollador | I2: =_xlfn.XLOOKUP(B2,BD!A:A,BD!C:C) -> Tecnología | J2: =_xlfn.XLOOKUP(B2,BD!A:A,BD!E:E) -> Bogotá | K2: =_xlfn.XLOOKUP(B2,BD!A:A,BD!F:F) -> 4200000 | L2: =D2*17500 -> 175000 | M2: =K2+L2+E2 -> 4625000 | N2: =IFERROR(_xlfn.IFS(M2>4000000, "SALARIO ALTO",M2>0, "SALARIO BAJO"),"SIN DATOS") -> SALARIO ALTO
A3: 46204 | B3: E002 | C3: 21 | D3: 8 | E3: 180000 | F3: 0 | G3: =_xlfn.XLOOKUP(B3,BD!A:A,BD!B:B) -> Juan Pérez | H3: =_xlfn.XLOOKUP(B3,BD!A:A,BD!D:D) -> Analista | I3: =_xlfn.XLOOKUP(B3,BD!A:A,BD!C:C) -> Tecnología | J3: =_xlfn.XLOOKUP(B3,BD!A:A,BD!E:E) -> Medellín | K3: =_xlfn.XLOOKUP(B3,BD!A:A,BD!F:F) -> 3900000 | L3: =D3*17500 -> 140000 | M3: =K3+L3+E3 -> 4220000 | N3: =IFERROR(_xlfn.IFS(M3>4000000, "SALARIO ALTO",M3>0, "SALARIO BAJO"),"SIN DATOS") -> SALARIO ALTO
A4: 46204 | B4: E003 | C4: 23 | D4: 12 | E4: 300000 | F4: 20000 | G4: =_xlfn.XLOOKUP(B4,BD!A:A,BD!B:B) -> Camila Torres | H4: =_xlfn.XLOOKUP(B4,BD!A:A,BD!D:D) -> Ejecutivo | I4: =_xlfn.XLOOKUP(B4,BD!A:A,BD!C:C) -> Ventas | J4: =_xlfn.XLOOKUP(B4,BD!A:A,BD!E:E) -> Cali | K4: =_xlfn.XLOOKUP(B4,BD!A:A,BD!F:F) -> 3200000 | L4: =D4*17500 -> 210000 | M4: =K4+L4+E4 -> 3710000 | N4: =IFERROR(_xlfn.IFS(M4>4000000, "SALARIO ALTO",M4>0, "SALARIO BAJO"),"SIN DATOS") -> SALARIO BAJO
A5: 46204 | B5: E004 | C5: 22 | D5: 5 | E5: 150000 | F5: 0 | G5: =_xlfn.XLOOKUP(B5,BD!A:A,BD!B:B) -> Andrés Ruiz | H5: =_xlfn.XLOOKUP(B5,BD!A:A,BD!D:D) -> Supervisor | I5: =_xlfn.XLOOKUP(B5,BD!A:A,BD!C:C) -> Ventas | J5: =_xlfn.XLOOKUP(B5,BD!A:A,BD!E:E) -> Bogotá | K5: =_xlfn.XLOOKUP(B5,BD!A:A,BD!F:F) -> 4500000 | L5: =D5*17500 -> 87500 | M5: =K5+L5+E5 -> 4737500 | N5: =IFERROR(_xlfn.IFS(M5>4000000, "SALARIO ALTO",M5>0, "SALARIO BAJO"),"SIN DATOS") -> SALARIO ALTO
A6: 46204 | B6: E005 | C6: 20 | D6: 4 | E6: 120000 | F6: 30000 | G6: =_xlfn.XLOOKUP(B6,BD!A:A,BD!B:B) -> Natalia Díaz | H6: =_xlfn.XLOOKUP(B6,BD!A:A,BD!D:D) -> Analista | I6: =_xlfn.XLOOKUP(B6,BD!A:A,BD!C:C) -> Recursos Humanos | J6: =_xlfn.XLOOKUP(B6,BD!A:A,BD!E:E) -> Medellín | K6: =_xlfn.XLOOKUP(B6,BD!A:A,BD!F:F) -> 3500000 | L6: =D6*17500 -> 70000 | M6: =K6+L6+E6 -> 3690000 | N6: =IFERROR(_xlfn.IFS(M6>4000000, "SALARIO ALTO",M6>0, "SALARIO BAJO"),"SIN DATOS") -> SALARIO BAJO
A7: 46204 | B7: E006 | C7: 22 | D7: 6 | E7: 200000 | F7: 0 | G7: =_xlfn.XLOOKUP(B7,BD!A:A,BD!B:B) -> Felipe Castro | H7: =_xlfn.XLOOKUP(B7,BD!A:A,BD!D:D) -> Contador | I7: =_xlfn.XLOOKUP(B7,BD!A:A,BD!C:C) -> Finanzas | J7: =_xlfn.XLOOKUP(B7,BD!A:A,BD!E:E) -> Bogotá | K7: =_xlfn.XLOOKUP(B7,BD!A:A,BD!F:F) -> 4300000 | L7: =D7*17500 -> 105000 | M7: =K7+L7+E7 -> 4605000 | N7: =IFERROR(_xlfn.IFS(M7>4000000, "SALARIO ALTO",M7>0, "SALARIO BAJO"),"SIN DATOS") -> SALARIO ALTO
A8: 46204 | B8: E007 | C8: 21 | D8: 7 | E8: 180000 | F8: 25000 | G8: =_xlfn.XLOOKUP(B8,BD!A:A,BD!B:B) -> Daniela Rojas | H8: =_xlfn.XLOOKUP(B8,BD!A:A,BD!D:D) -> Diseñador | I8: =_xlfn.XLOOKUP(B8,BD!A:A,BD!C:C) -> Marketing | J8: =_xlfn.XLOOKUP(B8,BD!A:A,BD!E:E) -> Cali | K8: =_xlfn.XLOOKUP(B8,BD!A:A,BD!F:F) -> 3600000 | L8: =D8*17500 -> 122500 | M8: =K8+L8+E8 -> 3902500 | N8: =IFERROR(_xlfn.IFS(M8>4000000, "SALARIO ALTO",M8>0, "SALARIO BAJO"),"SIN DATOS") -> SALARIO BAJO
A9: 46204 | B9: E008 | C9: 22 | D9: 3 | E9: 90000 | F9: 0 | G9: =_xlfn.XLOOKUP(B9,BD!A:A,BD!B:B) -> Carlos Herrera | H9: =_xlfn.XLOOKUP(B9,BD!A:A,BD!D:D) -> Soporte | I9: =_xlfn.XLOOKUP(B9,BD!A:A,BD!C:C) -> Tecnología | J9: =_xlfn.XLOOKUP(B9,BD!A:A,BD!E:E) -> Barranquilla | K9: =_xlfn.XLOOKUP(B9,BD!A:A,BD!F:F) -> 3100000 | L9: =D9*17500 -> 52500 | M9: =K9+L9+E9 -> 3242500 | N9: =IFERROR(_xlfn.IFS(M9>4000000, "SALARIO ALTO",M9>0, "SALARIO BAJO"),"SIN DATOS") -> SALARIO BAJO
A10: 46204 | B10: E009 | C10: 23 | D10: 9 | E10: 230000 | F10: 0 | G10: =_xlfn.XLOOKUP(B10,BD!A:A,BD!B:B) -> María López | H10: =_xlfn.XLOOKUP(B10,BD!A:A,BD!D:D) -> Coordinador | I10: =_xlfn.XLOOKUP(B10,BD!A:A,BD!C:C) -> Logística | J10: =_xlfn.XLOOKUP(B10,BD!A:A,BD!E:E) -> Bogotá | K10: =_xlfn.XLOOKUP(B10,BD!A:A,BD!F:F) -> 4100000 | L10: =D10*17500 -> 157500 | M10: =K10+L10+E10 -> 4487500 | N10: =IFERROR(_xlfn.IFS(M10>4000000, "SALARIO ALTO",M10>0, "SALARIO BAJO"),"SIN DATOS") -> SALARIO ALTO
A11: 46204 | B11: E010 | C11: 20 | D11: 2 | E11: 80000 | F11: 15000 | G11: =_xlfn.XLOOKUP(B11,BD!A:A,BD!B:B) -> Sebastián Gil | H11: =_xlfn.XLOOKUP(B11,BD!A:A,BD!D:D) -> Analista | I11: =_xlfn.XLOOKUP(B11,BD!A:A,BD!C:C) -> Compras | J11: =_xlfn.XLOOKUP(B11,BD!A:A,BD!E:E) -> Medellín | K11: =_xlfn.XLOOKUP(B11,BD!A:A,BD!F:F) -> 3400000 | L11: =D11*17500 -> 35000 | M11: =K11+L11+E11 -> 3515000 | N11: =IFERROR(_xlfn.IFS(M11>4000000, "SALARIO ALTO",M11>0, "SALARIO BAJO"),"SIN DATOS") -> SALARIO BAJO
A12: 46204 | B12: E011 | C12: 21 | D12: 4 | E12: 100000 | F12: 0 | G12: =_xlfn.XLOOKUP(B12,BD!A:A,BD!B:B) -> Paula Ramírez | H12: =_xlfn.XLOOKUP(B12,BD!A:A,BD!D:D) -> Community Manager | I12: =_xlfn.XLOOKUP(B12,BD!A:A,BD!C:C) -> Marketing | J12: =_xlfn.XLOOKUP(B12,BD!A:A,BD!E:E) -> Cali | K12: =_xlfn.XLOOKUP(B12,BD!A:A,BD!F:F) -> 3000000 | L12: =D12*17500 -> 70000 | M12: =K12+L12+E12 -> 3170000 | N12: =IFERROR(_xlfn.IFS(M12>4000000, "SALARIO ALTO",M12>0, "SALARIO BAJO"),"SIN DATOS") -> SALARIO BAJO
A13: 46204 | B13: E012 | C13: 22 | D13: 1 | E13: 50000 | F13: 0 | G13: =_xlfn.XLOOKUP(B13,BD!A:A,BD!B:B) -> David Sánchez | H13: =_xlfn.XLOOKUP(B13,BD!A:A,BD!D:D) -> Auxiliar | I13: =_xlfn.XLOOKUP(B13,BD!A:A,BD!C:C) -> Logística | J13: =_xlfn.XLOOKUP(B13,BD!A:A,BD!E:E) -> Barranquilla | K13: =_xlfn.XLOOKUP(B13,BD!A:A,BD!F:F) -> 2500000 | L13: =D13*17500 -> 17500 | M13: =K13+L13+E13 -> 2567500 | N13: =IFERROR(_xlfn.IFS(M13>4000000, "SALARIO ALTO",M13>0, "SALARIO BAJO"),"SIN DATOS") -> SALARIO BAJO
... A16: 46204 | B16: E015 | C16: 21 | D16: 6 | E16: 180000 | F16: 20000 | G16: =_xlfn.XLOOKUP(B16,BD!A:A,BD!B:B) -> Valentina Cruz | H16: =_xlfn.XLOOKUP(B16,BD!A:A,BD!D:D) -> Coordinador | I16: =_xlfn.XLOOKUP(B16,BD!A:A,BD!C:C) -> Recursos Humanos | J16: =_xlfn.XLOOKUP(B16,BD!A:A,BD!E:E) -> Cali | K16: =_xlfn.XLOOKUP(B16,BD!A:A,BD!F:F) -> 4200000 | L16: =D16*17500 -> 105000 | M16: =K16+L16+E16 -> 4485000 | N16: =IFERROR(_xlfn.IFS(M16>4000000, "SALARIO ALTO",M16>0, "SALARIO BAJO"),"SIN DATOS") -> SALARIO ALTO
K17: 100 | N17: =IFERROR(_xlfn.IFS(M17>4000000, "SALARIO ALTO",M17>0, "SALARIO BAJO"),"SIN DATOS") -> SIN DATOS

Sheet TABLA
A1: Fecha | B1: 46204
A3: Suma de Salario total | B3: Etiquetas de columna
A4: Etiquetas de fila | B4: Compras | C4: Finanzas | D4: Logística | E4: Marketing | F4: Recursos Humanos | G4: Tecnología | H4: Total general
A5: Carlos Herrera | G5: 3152500 | H5: 3152500
A6: Cristian León | G6: 4592500 | H6: 4592500
A7: Daniela Rojas | E7: 3722500 | H7: 3722500
A8: David Sánchez | D8: 2517500 | H8: 2517500
A9: Felipe Castro | C9: 4405000 | H9: 4405000
A10: Juan Pérez | G10: 4040000 | H10: 4040000
A11: Juliana Mora | C11: 3940000 | H11: 3940000
A12: Laura Gómez | G12: 4375000 | H12: 4375000
A13: María López | D13: 4257500 | H13: 4257500
A14: Natalia Díaz | F14: 3570000 | H14: 3570000
A15: Paula Ramírez | E15: 3070000 | H15: 3070000
A16: Sebastián Gil | B16: 3435000 | H16: 3435000
A17: Valentina Cruz | F17: 4305000 | H17: 4305000
A18: Total general | B18: 3435000 | C18: 8345000 | D18: 6775000 | E18: 6792500 | F18: 7875000 | G18: 16160000 | H18: 49382500

Sheet DASHBOARD
E1: Dashboard de Nómina y Recursos Humanos
L6: NOMINA TOTAL
L8: =SUM(DATOS!M:M) -> 60030000
L15: MAYOR SALARIO
L17: =MAX(DATOS!M:M) -> 4912500
L24: MENOR SALARIO
L26: =MIN(DATOS!M:M) -> 2567500
L33: HORAS EXTRA
L35: =SUM(DATOS!D:D) -> 96
L42: PROMEDIO SALARIAL
L44: =AVERAGE(DATOS!M:M) -> 4002000
